pykeadhcp/__init__.py
pykeadhcp/daemons/__init__.py
pykeadhcp/daemons/ctrlagent.py
pykeadhcp/daemons/ddns.py
pykeadhcp/daemons/dhcp4.py
pykeadhcp/daemons/dhcp6.py
pykeadhcp/exceptions.py
pykeadhcp/kea.py
pykeadhcp/models/__init__.py
pykeadhcp/models/ctrlagent/__init__.py
pykeadhcp/models/ctrlagent/config.py
pykeadhcp/models/dhcp4/__init__.py
pykeadhcp/models/dhcp4/client_class.py
pykeadhcp/models/dhcp4/config.py
pykeadhcp/models/dhcp4/lease.py
pykeadhcp/models/dhcp4/reservation.py
pykeadhcp/models/dhcp4/shared_network.py
pykeadhcp/models/dhcp4/subnet.py
pykeadhcp/models/dhcp6/__init__.py
pykeadhcp/models/dhcp6/client_class.py
pykeadhcp/models/dhcp6/config.py
pykeadhcp/models/dhcp6/lease.py
pykeadhcp/models/dhcp6/pd_pool.py
pykeadhcp/models/dhcp6/reservation.py
pykeadhcp/models/dhcp6/server_id.py
pykeadhcp/models/dhcp6/shared_network.py
pykeadhcp/models/dhcp6/subnet.py
pykeadhcp/models/enums.py
pykeadhcp/models/generic/__init__.py
pykeadhcp/models/generic/api_response.py
pykeadhcp/models/generic/authentication.py
pykeadhcp/models/generic/base.py
pykeadhcp/models/generic/client_class.py
pykeadhcp/models/generic/config.py
pykeadhcp/models/generic/control_socket.py
pykeadhcp/models/generic/daemon.py
pykeadhcp/models/generic/database.py
pykeadhcp/models/generic/dhcp_common.py
pykeadhcp/models/generic/dhcp_ddns.py
pykeadhcp/models/generic/dhcp_queue_control.py
pykeadhcp/models/generic/hook.py
pykeadhcp/models/generic/lease.py
pykeadhcp/models/generic/logger.py
pykeadhcp/models/generic/multi_threading.py
pykeadhcp/models/generic/option_data.py
pykeadhcp/models/generic/option_def.py
pykeadhcp/models/generic/pool.py
pykeadhcp/models/generic/relay.py
pykeadhcp/models/generic/remote_map.py
pykeadhcp/models/generic/remote_server.py
pykeadhcp/models/generic/reservation.py
pykeadhcp/models/generic/sanity_check.py
pykeadhcp/models/generic/shared_network.py
pykeadhcp/models/generic/sockets.py
pykeadhcp/models/generic/status.py
pykeadhcp/models/generic/subnet.py
pykeadhcp-0.6.0.dist-info/LICENSE
pykeadhcp-0.6.0.dist-info/METADATA
pykeadhcp-0.6.0.dist-info/WHEEL
pykeadhcp-0.6.0.dist-info/RECORD
