Metadata-Version: 2.1
Name: pykeadhcp
Version: 0.6.0
Summary: Wrapper around requests module to query ISC Kea DHCP API Daemons (ctrlagent, dhcp4, dhcp6, ddns)
License: Apache 2.0
Author: Brandon Spendlove
Author-email: brandon-spendlove@hotmail.co.uk
Requires-Python: >=3.10,<4.0
Classifier: License :: Other/Proprietary License
Classifier: Programming Language :: Python :: 3
Classifier: Programming Language :: Python :: 3.10
Classifier: Programming Language :: Python :: 3.11
Requires-Dist: pydantic (>=1.10.8,<2.0.0)
Requires-Dist: requests (>=2.31.0,<3.0.0)
